[
  {
    "title": "Koonawarra",
    "price": 550,
    "description": "5 minutes walking to Everyday Supermarket.",
    "furnished": false,
    "walkingToMonash": 5,
    "walkingToBusStop": 4,
    "sourceURL": "https://www.realestate.com.au/property-house-vic-clayton-442585220",
    "imageURL": "https://i2.au.reastatic.net/1000x750-format=webp/a947e304ae15bde6601a0dbcb0bb86ced4b54867b1e891030c41a1707282191d/image.jpg",
    "lat": -37.90932891659748,
    "lon": 145.12459269439213
  },
  {
    "title": "1 Dobson Avenue, Oakleigh East, Vic 3166",
    "price": 750,
    "description": "Walking distance to Monash. No info on utilities.",
    "furnished": false,
    "walkingToMonash": 23,
    "walkingToBusStop": 2,
    "sourceURL": "https://www.realestate.com.au/property-house-vic-oakleigh+east-442150092?sourcePage=rea:rent:srp-map&sourceElement=listing-tile",
    "imageURL": "https://i2.au.reastatic.net/800x600-format=webp/cd865a917944d74fef60666e6824e7b8c432a7449a5fd45bcd36c343726f8293/image.jpg",
    "lat": -37.90577935690792,
    "lon": 145.121755272132
  },
  {
    "title": "7 Browns Court, Clayton, Vic 3168",
    "price": 800,
    "description": "No info on utilities. Has A/C & Heating duct. Around 34 minutes walking to Monash.",
    "furnished": false,
    "walkingToMonash": 5,
    "walkingToBusStop": 4,
    "sourceURL": "https://www.realestate.com.au/property-house-vic-clayton-439725576?sourcePage=rea:rent:srp-map&sourceElement=listing-tile",
    "imageURL": "https://i2.au.reastatic.net/800x600-format=webp/5b431c6e2346b5edfad58af83583f6ec49b75e4499802b0b6492e26842fbd28a/image.jpg",
    "lat": -37.91613379569678,
    "lon": 145.12687776110204
  },
  {
    "title": "1/6 Jean Avenue, Clayton, Vic 3168",
    "price": 800,
    "description": "3 toilets, 2-story townhouse. Very close to public transport. Close to Clayton shopping plaza. Unfurnished. No info on utilities. Has A/C.",
    "furnished": false,
    "walkingToMonash": 30,
    "walkingToBusStop": 7,
    "sourceURL": "https://www.realestate.com.au/property-townhouse-vic-clayton-436495044?sourcePage=rea:rent:srp-map&sourceElement=listing-tile",
    "imageURL": "https://i2.au.reastatic.net/800x600-format=webp/4edb5ace9830126cf53de3266c7cc0890894b8e85ff128cb1c683a06cb2f0c6b/image.jpg",
    "lat": -37.92700946653838,
    "lon": 145.1216438547458
  },
  {
    "title": "2/1925 Dandenong Road, Clayton, Vic 3168",
    "price": 850,
    "description": "No info on utilities. 5 minutes walking to Monash.",
    "furnished": false,
    "walkingToMonash": 5,
    "walkingToBusStop": 2,
    "sourceURL": "https://www.realestate.com.au/property-townhouse-vic-clayton-442519600?sourcePage=rea:rent:srp-map&sourceElement=listing-tile",
    "imageURL": "https://i2.au.reastatic.net/800x600-format=webp/ed9c8cfb0eefd890a1adb78103c67927a0fb7e4693c845ab730b7bd33037d093/image.jpg",
    "lat": -37.911567273502726,
    "lon": 145.12365196823876
  },
  {
    "title": "56 Browns Road, Clayton, Vic 3168",
    "price": 500,
    "description": "No utilities. Gas heating and A/C. 6 minutes driving to Monash. 18–25 minutes walking to Clayton Shopping Plaza. Agent: A/Real.",
    "furnished": false,
    "walkingToMonash": 20,
    "walkingToBusStop": 11,
    "sourceURL": "https://www.realestate.com.au/property-house-vic-clayton-442666192?sourcePage=rea:rent:srp-map&sourceElement=listing-tile",
    "imageURL": "https://i2.au.reastatic.net/800x600-resize,extend,r=33,g=40,b=46/1e6d425eafa01fc183a2445c7297ba093653408f156a1facc3dfce11d90228db/image.jpg",
    "lat": -37.92325550054864,
    "lon": 145.12653744125205
  },
  {
    "title": "4/115 Warrigal Road, Oakleigh, Melbourne",
    "price": 520,
    "description": "No utilities. 9 minutes driving to Monash. 0.38 km to supermarket. Agent: Unconfirmed.",
    "furnished": false,
    "walkingToMonash": 70,
    "walkingToBusStop": 7,
    "sourceURL": "https://en.uhomes.com/au/melbourne/detail-apartments-1568082?schoolunique=monash-university-clayton-campus",
    "imageURL": "https://media.uhzcdn.com/image/1393/01HVHES644W9VC4T6N7PWNHEFP_g.webp",
    "lat": -37.90228923000047,
    "lon": 145.08613998173195
  },
  {
    "title": "17 Arunta Crescent, Clarinda, Vic 3169",
    "price": 550,
    "description": "No utilities. System heating and A/C. 11 minutes driving to Monash. 18–25 minutes walking to Clayton Shopping Plaza. Agent: Century 21.",
    "furnished": false,
    "walkingToMonash": 58,
    "walkingToBusStop": 5,
    "sourceURL": "https://www.realestate.com.au/property-house-vic-clarinda-419826782?sourcePage=rea:rent:srp-map&sourceElement=listing-tile",
    "imageURL": "https://i2.au.reastatic.net/800x600-format=webp/b3cafc0490dcf193828d17bcea23ba8781163b1323a459090f43ac5a4b4e0e1c/image.jpg",
    "lat": -37.92856925616889,
    "lon": 145.10733899892324
  },
  {
    "title": "2/20 Irwin Street, Clayton, Vic 3168",
    "price": 580,
    "description": "No utilities. Floorboard heating. 13 minutes walking to Monash. 13 minutes walking to Woolworths. Agent: Everestar.",
    "furnished": false,
    "walkingToMonash": 13,
    "walkingToBusStop": 8,
    "sourceURL": "https://www.realestate.com.au/property-unit-vic-clayton-442595556?sourcePage=rea:rent:srp-map&sourceElement=listing-tile",
    "imageURL": "https://i2.au.reastatic.net/800x600-format=webp/26481787ec152d89c91de9b324fde123cdb034db837e1a43b71ad5c8df9ff26b/image.jpg",
    "lat": -37.91727244521091,
    "lon": 145.1338430817327
  },
  {
    "title": "2/9-11 Dixon St, Clayton, Vic 3168",
    "price": 595,
    "description": "Partially furnished. No utilities. 6 minutes driving to Monash. 5 minutes driving to M-City. 16 minutes walking to supermarket. Agent: Trans Rental.",
    "furnished": true,
    "walkingToMonash": 15,
    "walkingToBusStop": 8,
    "sourceURL": "https://www.realestate.com.au/property-townhouse-vic-clayton-442650544?sourcePage=rea:rent:srp-map&sourceElement=listing-tile",
    "imageURL": "https://i2.au.reastatic.net/800x600-format=webp/1a03d7247d7dd77d6185b1e1a568a0272cbdae482d53a7c16f52d6ee47f031b9/image.jpg",
    "lat": -37.91876764116501,
    "lon": 145.12246017008715
  },
  {
    "title": "3/16 Prince Street, Clayton, Vic 3168",
    "price": 630,
    "description": "Unfurnished. No info on utilities. 30 minutes walking (2.1 km) to Monash. 21–25 minutes walking to Clayton Shopping Plaza. 21 minutes walking to Coles Clayton. Agent: RayWhite.",
    "furnished": false,
    "walkingToMonash": 15,
    "walkingToBusStop": 10,
    "sourceURL": "https://www.realestate.com.au/property-townhouse-vic-clayton-434673563?sourcePage=rea:rent:srp-map&sourceElement=listing-tile",
    "imageURL": "https://i2.au.reastatic.net/800x600-format=webp/c1f8813c9209698004ea484455e6cb116acec7a1e6d47d6534ac1f8e8afc72af/image.jpg",
    "lat": -37.916817983772184,
    "lon": 145.12441476639071
  },
  {
    "title": "26 Calista Avenue, Oakleigh East, Vic 3166",
    "price": 630,
    "description": "Furnished. No info on utilities. 6 minutes driving / 22 minutes walking to Monash. 16 minutes walking to supermarket. Agent: AUSpacific.",
    "furnished": true,
    "walkingToMonash": 22,
    "walkingToBusStop": 17,
    "sourceURL": "https://www.realestate.com.au/property-house-vic-oakleigh+east-442493656?sourcePage=rea:rent:srp-map&sourceElement=listing-tile",
    "imageURL": "https://i2.au.reastatic.net/800x600-format=webp/a146a0c41a7728f4012414d1ab55a87313709a7cc0c2a55e14754608a08b89ea/image.jpg",
    "lat": -37.9038461035059,
    "lon": 145.12264359522578
  },
  {
    "title": "Arnott Street Apartment",
    "price": 520,
    "description": "Partially furnished apartment near Monash University Clayton. Steps from campus, public transport, train station, Monash Medical Centre, and shopping centre. Includes open-plan living, gas cooktop, A/C, and private balcony.",
    "furnished": true,
    "walkingToMonash": 2,
    "walkingToBusStop": 6,
    "sourceURL": "https://www.realestate.com.au/property-apartment-vic-clayton-442578156",
    "imageURL": "https://i2.au.reastatic.net/800x600-resize,extend,r=33,g=40,b=46/fcaeaebe77ed4d562f483c37ef40f73eeac6cef81c0f1eb003541e2449537c85/image.jpg",
    "lat": -37.91652678320265,
    "lon": 145.13513789892255
  }
]